{"cameraMode":{"drawMode":0,"name":"Shaded","section":"Shading Mode"},"sceneLighting":true,"audioPlay":false,"sceneViewState":{"m_AlwaysRefresh":false,"showFog":true,"showSkybox":true,"showFlares":true,"showImageEffects":true,"showParticleSystems":true,"showVisualEffectGraphs":true,"m_FxEnabled":true},"in2DMode":false,"pivot":{"x":-69.77892303466797,"y":-25.261676788330079,"z":-1.263298749923706},"rotation":{"x":-0.17137666046619416,"y":0.6890707015991211,"z":-0.17300066351890565,"w":-0.6824901700019836},"size":38.388797760009769,"orthographic":false}